vlm_navigation/__init__.py
vlm_navigation/inference.py
vlm_navigation/prompt_manager/navigation_prompt.txt
vlm_inference-0.1.36.dist-info/METADATA
vlm_inference-0.1.36.dist-info/WHEEL
vlm_inference-0.1.36.dist-info/top_level.txt
vlm_inference-0.1.36.dist-info/RECORD
