Metadata-Version: 2.4
Name: vlm_inference
Version: 0.1.36
Summary: Vision language models for robotics
Home-page: https://gitlab.iri.upc.edu/mobile_robotics/moonshot_project/vlm/vlm_inference
Author: Edison Bejarano
Author-email: Edison Bejarano <edison.bejarano@upc.edu>
License: MIT
Requires-Dist: openai==1.78.1
Requires-Dist: opencv-python==4.11.0.86
Requires-Dist: pyyaml
Requires-Dist: python-dotenv<0.11,==0.9.1
Requires-Dist: Pillow==9.0.1
Dynamic: author
Dynamic: home-page
